finch/__init__.py
finch/finch.py
finch/finch_utils.py
finch_clust-0.2.2.dist-info/licenses/LICENSE.txt
finch_clust-0.2.2.dist-info/METADATA
finch_clust-0.2.2.dist-info/WHEEL
finch_clust-0.2.2.dist-info/top_level.txt
finch_clust-0.2.2.dist-info/RECORD
