Metadata-Version: 2.4
Name: finch-clust
Version: 0.2.2
Summary: FINCH - First Integer Neighbor Clustering Hierarchy: A parameter-free fast clustering algorithm.
Author: Saquib Sarfraz
Author-email: saquibsarfraz@gmail.com
Project-URL: Repository, https://github.com/ssarfraz/FINCH-Clustering
Project-URL: Publication, https://openaccess.thecvf.com/content_CVPR_2019/html/Sarfraz_Efficient_Parameter-Free_Clustering_Using_First_Neighbor_Relations_CVPR_2019_paper.html
Classifier: Development Status :: 5 - Production/Stable
Classifier: Operating System :: MacOS
Classifier: Operating System :: Unix
Classifier: Programming Language :: Python :: 3.8
Classifier: Programming Language :: Python :: 3.9
Classifier: Programming Language :: Python :: 3.10
Classifier: Programming Language :: Python :: 3.11
Classifier: Programming Language :: Python :: 3.12
Requires-Python: >=3.8
License-File: LICENSE.txt
Requires-Dist: scipy
Requires-Dist: scikit-learn
Requires-Dist: numpy
Provides-Extra: ann
Requires-Dist: pynndescent; extra == "ann"
Dynamic: author
Dynamic: author-email
Dynamic: classifier
Dynamic: description
Dynamic: description-content-type
Dynamic: license-file
Dynamic: project-url
Dynamic: provides-extra
Dynamic: requires-dist
Dynamic: requires-python
Dynamic: summary
